threaded/__init__.py
threaded/_asynciotask.py
threaded/_base_threaded.py
threaded/_threaded.py
threaded/_threadpooled.py
threaded/_version.py
threaded/class_decorator.py
threaded/py.typed
threaded-4.1.0.dist-info/LICENSE
threaded-4.1.0.dist-info/METADATA
threaded-4.1.0.dist-info/WHEEL
threaded-4.1.0.dist-info/top_level.txt
threaded-4.1.0.dist-info/RECORD
