Metadata-Version: 1.2
Name: threaded
Version: 4.1.0
Summary: Decorators for running functions in Thread/ThreadPool/IOLoop
Home-page: https://github.com/python-useful-helpers/threaded
Author: Alexey Stepanov
Author-email: penguinolog@gmail.com
Maintainer: Alexey Stepanov <penguinolog@gmail.com>, Antonio Esposito <esposito.cloud@gmail.com>, Dennis Dmitriev <dis-xcom@gmail.com>
License: Apache License, Version 2.0
Project-URL: Bug Tracker, https://github.com/python-useful-helpers/threaded/issues
Project-URL: Documentation, https://threaded.readthedocs.io/
Keywords: pooling,multithreading,threading,asyncio,development
Platform: UNKNOWN
Classifier: Development Status :: 5 - Production/Stable
Classifier: Intended Audience :: Developers
Classifier: Topic :: Software Development :: Libraries :: Python Modules
Classifier: License :: OSI Approved :: Apache Software License
Classifier: Programming Language :: Python :: 3
Classifier: Programming Language :: Python :: 3.6
Classifier: Programming Language :: Python :: 3.7
Classifier: Programming Language :: Python :: 3.8
Classifier: Programming Language :: Python :: 3.9
Classifier: Programming Language :: Python :: Implementation :: CPython
Classifier: Programming Language :: Python :: Implementation :: PyPy
Requires-Python: >=3.6.0
